Metadata-Version: 1.1
Name: sphinxcontrib-merge
Version: 0.1.0
Summary: Build Sphinx documentation from multiple remote sources.
Home-page: https://github.com/dgarcia360/sphinxcontrib-merge
Author: David Garcia
Author-email: dgarcia360@outlook.com
License: MIT
Download-URL: http://pypi.python.org/pypi/sphinxcontrib-merge
Platform: any
Classifier: License :: OSI Approved :: MIT License
Classifier: Topic :: Documentation
Classifier: Topic :: Utilities
Classifier: Programming Language :: Python :: 2
Classifier: Programming Language :: Python :: 3
